mxlbricks/__init__.py
mxlbricks/derived.py
mxlbricks/fns.py
mxlbricks/models.py
mxlbricks/names.py
mxlbricks/py.typed
mxlbricks/utils.py
mxlbricks/enzymes/__init__.py
mxlbricks/enzymes/_create_imports.py
mxlbricks/enzymes/_placeholder.py
mxlbricks/enzymes/_transaldolase_f6p_a5p_o8p_gap.py
mxlbricks/enzymes/_transaldolase_f6p_e4p_s7p_gap.py
mxlbricks/enzymes/_transketolase_f6p_g6p_o8p_e4p.py
mxlbricks/enzymes/_transketolase_f6p_r5p_s7p_e4p.py
mxlbricks/enzymes/_transketolase_neutral.py
mxlbricks/enzymes/_transketolase_s7p_g6p_o8p_r5p.py
mxlbricks/enzymes/_transketolase_x5p_g6p_o8p_gap.py
mxlbricks/enzymes/a5p_isomerase.py
mxlbricks/enzymes/acetoacetate_coa_ligase.py
mxlbricks/enzymes/acetyl_coa_acetyltransfer.py
mxlbricks/enzymes/acetyl_coa_carboxyltransfer.py
mxlbricks/enzymes/aldolase_dhap_a5p_obp.py
mxlbricks/enzymes/aldolase_dhap_e4p_sbp.py
mxlbricks/enzymes/aldolase_dhap_gap_fbp.py
mxlbricks/enzymes/aldolase_gah_dhap_r1p.py
mxlbricks/enzymes/aldolase_gah_gap_a5p.py
mxlbricks/enzymes/aldolase_glyoyx_gly_ha.py
mxlbricks/enzymes/ascorbate_perixodase.py
mxlbricks/enzymes/aspartate_aminotransferase.py
mxlbricks/enzymes/aspartate_nad_oxidoreductase.py
mxlbricks/enzymes/aspartate_nadp_oxidoreductase.py
mxlbricks/enzymes/atp_synthase.py
mxlbricks/enzymes/b6f.py
mxlbricks/enzymes/carbonic_anhydrase.py
mxlbricks/enzymes/catalase.py
mxlbricks/enzymes/cef.py
mxlbricks/enzymes/co2_dissolving.py
mxlbricks/enzymes/dehydroascorbate_reductase.py
mxlbricks/enzymes/e4p_epimerase.py
mxlbricks/enzymes/e4p_isomerase.py
mxlbricks/enzymes/enolase.py
mxlbricks/enzymes/erythrolose_kinase.py
mxlbricks/enzymes/ex_atp.py
mxlbricks/enzymes/ex_g1p.py
mxlbricks/enzymes/ex_nadph.py
mxlbricks/enzymes/fbpase.py
mxlbricks/enzymes/fd_reductase.py
mxlbricks/enzymes/fnr.py
mxlbricks/enzymes/formate_dehydrogenase.py
mxlbricks/enzymes/formate_thf_ligase.py
mxlbricks/enzymes/g6pi.py
mxlbricks/enzymes/gadph.py
mxlbricks/enzymes/glutamate_dehydrogenase.py
mxlbricks/enzymes/glutathion_reductase.py
mxlbricks-0.6.0.dist-info/METADATA
mxlbricks-0.6.0.dist-info/WHEEL
mxlbricks-0.6.0.dist-info/RECORD
