Metadata-Version: 2.4
Name: mxlbricks
Version: 0.6.0
Summary: A package to build metabolic models
Author-email: Marvin van Aalst <marvin.vanaalst@gmail.com>
Maintainer-email: Marvin van Aalst <marvin.vanaalst@gmail.com>
License-Expression: MIT
Keywords: metabolic,modelling,ode
Classifier: Development Status :: 5 - Production/Stable
Classifier: Environment :: Console
Classifier: Intended Audience :: Developers
Classifier: Intended Audience :: Science/Research
Classifier: License :: OSI Approved :: MIT License
Classifier: Operating System :: MacOS
Classifier: Operating System :: Microsoft :: Windows
Classifier: Operating System :: OS Independent
Classifier: Operating System :: POSIX
Classifier: Operating System :: Unix
Classifier: Programming Language :: Python :: 3
Classifier: Programming Language :: Python :: 3.11
Classifier: Topic :: Scientific/Engineering
Classifier: Topic :: Software Development
Requires-Python: >=3.12
Requires-Dist: mxlpy>=0.26.0
